README.md
setup.cfg
setup.py
easy_td/__init__.py
easy_td.egg-info/PKG-INFO
easy_td.egg-info/SOURCES.txt
easy_td.egg-info/dependency_links.txt
easy_td.egg-info/top_level.txt
easy_td/__endpoints__/instruments.py
easy_td/__endpoints__/option_chains.py
easy_td/__endpoints__/symbols.py
easy_td/__utlity__/bell.py
easy_td/__utlity__/config.py
easy_td/__utlity__/fetcher.py