Metadata-Version: 2.1
Name: easy-td
Version: 0.2
Summary: A declarative library for making the TD Ameritrade API more accessible
Home-page: https://github.com/ltanedo/easy-td.git
Download-URL: https://github.com/ltanedo/easy-td/archive/refs/tags/v_02.tar.gz
Author: lloydtan
Author-email: lloydtan@buffalo.edu
License: MIT
Keywords: python,algo,trading,data,stocks,stock,td,ameritrade
Platform: UNKNOWN
Classifier: Development Status :: 3 - Alpha
Classifier: Intended Audience :: Developers
Classifier: Topic :: Software Development :: Build Tools
Classifier: License :: OSI Approved :: MIT License
Classifier: Programming Language :: Python :: 3
Classifier: Programming Language :: Python :: 3.4
Classifier: Programming Language :: Python :: 3.5
Classifier: Programming Language :: Python :: 3.6
Classifier: Programming Language :: Python :: 3.8
